traingame/__init__.py
traingame/__main__.py
traingame/__version__.py
traingame/bresenham.py
traingame/cli.py
traingame/game.py
traingame/player.py
traingame/training.py
traingame/visualize.py
traingame/config/config-feedforward-assen-speed.cfg
traingame/config/config-feedforward-assen.cfg
traingame/config/config-feedforward.cfg
traingame/config/config-feedforward2.cfg
traingame/config/config-feedforwardspeed.cfg
traingame/models/almost_better.pickle
traingame/models/assen-127.pickle
traingame/models/assen-198.pickle
traingame/models/finish-assen-distance.pickle
traingame/models/finish-assen-speed.pickle
traingame/tracks/assen/track.png
traingame/tracks/assen/track_bg.png
traingame/tracks/assen-mirror/track.png
traingame/tracks/assen-mirror/track_bg.png
traingame/tracks/monaco/track.png
traingame/tracks/monaco/track_bg.png
traingame/tracks/monaco-mirror/track.png
traingame/tracks/monaco-mirror/track_bg.png
traingame/visuals/icon.png
traingame/visuals/roboto.ttf
traingame/visuals/train-blue.png
traingame/visuals/train-green.png
traingame/visuals/train-white.png
traingame/visuals/train.png
traingame-0.4.0.dist-info/LICENSE
traingame-0.4.0.dist-info/METADATA
traingame-0.4.0.dist-info/WHEEL
traingame-0.4.0.dist-info/entry_points.txt
traingame-0.4.0.dist-info/top_level.txt
traingame-0.4.0.dist-info/RECORD
