Metadata-Version: 2.1
Name: traingame
Version: 0.4.0
Summary: Train your own AI and race it!
Home-page: UNKNOWN
Author: Timo Lesterhuis
Author-email: timo.lesterhuis@nl.ey.com
License: UNKNOWN
Platform: UNKNOWN
Classifier: Programming Language :: Python :: 3
Classifier: License :: OSI Approved :: MIT License
Classifier: Operating System :: OS Independent
Requires-Python: >=3.6
Requires-Dist: pygame
Requires-Dist: numpy
Requires-Dist: Pillow
Requires-Dist: loguru
Requires-Dist: neat-python
Requires-Dist: matplotlib
Requires-Dist: typer
